makehash/__init__.py
makehash/__main__.py
makehash/entry_points_console_scripts.py
makehash/main.py
makehash-0.1.5.dist-info/entry_points.txt
makehash-0.1.5.dist-info/LICENSE
makehash-0.1.5.dist-info/WHEEL
makehash-0.1.5.dist-info/METADATA
makehash-0.1.5.dist-info/RECORD
